WonderPeaks_preprocessing/LICENSE
WonderPeaks_preprocessing/NGS_preprocessing.py
WonderPeaks_preprocessing/QC.py
WonderPeaks_preprocessing/STAR_alignment.py
WonderPeaks_preprocessing/__init__.py
WonderPeaks_preprocessing/bamCoverage.py
WonderPeaks_preprocessing/environment.yml
WonderPeaks_preprocessing/fastp.py
WonderPeaks_preprocessing/feature_counts.py
WonderPeaks_preprocessing/split_directories.py
WonderPeaks_preprocessing/user_inputs.py
WonderPeaks_preprocessing/NGS_user_files/NGS_user_inputs.csv
WonderPeaks_preprocessing/NGS_user_files/NGS_user_metadata.csv
WonderPeaks_preprocessing/Notebooks/NGS_processing.ipynb
wonderpeaks_preprocessing-0.2.4.dist-info/METADATA
wonderpeaks_preprocessing-0.2.4.dist-info/WHEEL
wonderpeaks_preprocessing-0.2.4.dist-info/top_level.txt
wonderpeaks_preprocessing-0.2.4.dist-info/RECORD
